anthros/__init__.py
anthros/core.py
anthros/extens/__init__.py
anthros/extens/data.class
anthros/extens/fold.class
anthros/extens/imports.pre
anthros/extens/imports.pst
anthros/extens/ini.class
anthros/extens/mp3.class
anthros/extens/path.class
anthros/extens/txt.class
anthros/interfaces/__init__.py
anthros/interfaces/console.py
anthros/project/__init__.py
anthros/project/conf.ini
anthros/project/manifest.ini
anthros/project/run.bat
anthros/project/run.py
anthros/project/test.py
anthros/tools/__init__.py
anthros/tools/assembly.py
anthros/tools/info.py
anthros/tools/manager.py
anthros/tools/represent.py
anthros/tools/simple.py
anthros/tools/stdinout.py
anthros_core-1.1.dist-info/LICENSE
anthros_core-1.1.dist-info/METADATA
anthros_core-1.1.dist-info/WHEEL
anthros_core-1.1.dist-info/top_level.txt
anthros_core-1.1.dist-info/RECORD
