Metadata-Version: 2.1
Name: anthros-core
Version: 1.1
Summary: environment, interfaces, tools and environment for development, testing
Home-page: https://vk.com/anthros
Author: Tand
Author-email: thunder.light.pegasys@gmail.com
Project-URL: Bug Tracker, https://vk.com/anthros
Classifier: Programming Language :: Python :: 3
Classifier: License :: OSI Approved :: GNU General Public License v3 or later (GPLv3+)
Classifier: Development Status :: 3 - Alpha
Classifier: Environment :: Console
Classifier: Operating System :: OS Independent
Requires-Python: >=3.6
License-File: LICENSE
